iamjjintta/__init__.py
iamjjintta/iamjjintta.py
iamjjintta-0.0.1.dist-info/METADATA
iamjjintta-0.0.1.dist-info/WHEEL
iamjjintta-0.0.1.dist-info/top_level.txt
iamjjintta-0.0.1.dist-info/RECORD
